{
  "specName": "Devourer",
  "className": "Demon Hunter",
  "talents": {
    "90942": {
      "name": "Vengeful Retreat",
      "icon": "ability_demonhunter_vengefulretreat2",
      "spellId": 198793
    },
    "117858": {
      "name": "Vengeful Retreat",
      "icon": "ability_demonhunter_vengefulretreat2",
      "spellId": 198793
    },
    "90946": {
      "name": "Sigil of Misery",
      "icon": "ability_demonhunter_sigilofmisery",
      "spellId": 207684
    },
    "117864": {
      "name": "Sigil of Misery",
      "icon": "ability_demonhunter_sigilofmisery",
      "spellId": 207684
    },
    "90930": {
      "name": "Vengeful Bonds",
      "icon": "ability_demonhunter_vengefulretreat2",
      "spellId": 320635
    },
    "117845": {
      "name": "Vengeful Bonds",
      "icon": "ability_demonhunter_vengefulretreat2",
      "spellId": 320635
    },
    "90941": {
      "name": "Unrestrained Fury",
      "icon": "ability_warrior_improveddisciplines",
      "spellId": 320770
    },
    "117857": {
      "name": "Unrestrained Fury",
      "icon": "ability_warrior_improveddisciplines",
      "spellId": 320770
    },
    "90950": {
      "name": "Shattered Restoration",
      "icon": "ability_warlock_soulsiphon",
      "spellId": 389824
    },
    "117868": {
      "name": "Shattered Restoration",
      "icon": "ability_warlock_soulsiphon",
      "spellId": 389824
    },
    "90945": {
      "name": "Improved Sigil of Misery",
      "icon": "ability_demonhunter_sigilofmisery",
      "spellId": 320418
    },
    "117863": {
      "name": "Improved Sigil of Misery",
      "icon": "ability_demonhunter_sigilofmisery",
      "spellId": 320418
    },
    "90931": {
      "name": "Bouncing Glaives",
      "icon": "ability_demonhunter_throwglaive",
      "spellId": 320386
    },
    "117846": {
      "name": "Bouncing Glaives",
      "icon": "ability_demonhunter_throwglaive",
      "spellId": 320386
    },
    "91007": {
      "name": "Imprison",
      "icon": "ability_demonhunter_imprison",
      "spellId": 217832
    },
    "117932": {
      "name": "Imprison",
      "icon": "ability_demonhunter_imprison",
      "spellId": 217832
    },
    "90948": {
      "name": "Charred Warblades",
      "icon": "spell_fire_incinerate",
      "spellId": 213010
    },
    "117866": {
      "name": "Charred Warblades",
      "icon": "spell_fire_incinerate",
      "spellId": 213010
    },
    "107347": {
      "name": "Void Nova",
      "icon": "inv_12_voiddh_ability_voidnova",
      "spellId": 1234195
    },
    "137090": {
      "name": "Void Nova",
      "icon": "inv_12_voiddh_ability_voidnova",
      "spellId": 1234195
    },
    "90938": {
      "name": "Improved Disrupt",
      "icon": "ability_demonhunter_consumemagic",
      "spellId": 320361
    },
    "117854": {
      "name": "Improved Disrupt",
      "icon": "ability_demonhunter_consumemagic",
      "spellId": 320361
    },
    "91006": {
      "name": "Consume Magic",
      "icon": "spell_misc_zandalari_council_soulswap",
      "spellId": 278326
    },
    "117931": {
      "name": "Consume Magic",
      "icon": "spell_misc_zandalari_council_soulswap",
      "spellId": 278326
    },
    "90999": {
      "name": "Aldrachi Design",
      "icon": "inv_glaive_1h_artifactaldrochi_d_01dual",
      "spellId": 391409
    },
    "117922": {
      "name": "Aldrachi Design",
      "icon": "inv_glaive_1h_artifactaldrochi_d_01dual",
      "spellId": 391409
    },
    "95154": {
      "name": "Focused Ire",
      "icon": "ability_bossfellord_felspike",
      "spellId": 1266296
    },
    "122779": {
      "name": "Focused Ire",
      "icon": "ability_bossfellord_felspike",
      "spellId": 1266296
    },
    "90994": {
      "name": "Master of the Glaive",
      "icon": "inv_glaive_1h_demonhunter_a_01",
      "spellId": 389763
    },
    "117917": {
      "name": "Master of the Glaive",
      "icon": "inv_glaive_1h_demonhunter_a_01",
      "spellId": 389763
    },
    "122780": {
      "name": "Champion of the Glaive",
      "icon": "inv_glaive_1h_battledungeon_c_01",
      "spellId": 429211
    },
    "90937": {
      "name": "Disrupting Fury",
      "icon": "ability_demonhunter_consumemagic",
      "spellId": 183782
    },
    "117853": {
      "name": "Disrupting Fury",
      "icon": "ability_demonhunter_consumemagic",
      "spellId": 183782
    },
    "95150": {
      "name": "Blazing Path",
      "icon": "ability_demonhunter_felrush",
      "spellId": 320416
    },
    "122771": {
      "name": "Blazing Path",
      "icon": "ability_demonhunter_felrush",
      "spellId": 320416
    },
    "91005": {
      "name": "Swallowed Anger",
      "icon": "spell_misc_zandalari_council_soulswap",
      "spellId": 320313
    },
    "117930": {
      "name": "Swallowed Anger",
      "icon": "spell_misc_zandalari_council_soulswap",
      "spellId": 320313
    },
    "90933": {
      "name": "Aura of Pain",
      "icon": "spell_fire_felimmolation",
      "spellId": 207347
    },
    "117849": {
      "name": "Aura of Pain",
      "icon": "spell_fire_felimmolation",
      "spellId": 207347
    },
    "95151": {
      "name": "Live by the Glaive",
      "icon": "inv_sword_108",
      "spellId": 428607
    },
    "122773": {
      "name": "Live by the Glaive",
      "icon": "inv_sword_108",
      "spellId": 428607
    },
    "90940": {
      "name": "Pursuit",
      "icon": "ability_demonhunter_infernalstrike2",
      "spellId": 320654
    },
    "117856": {
      "name": "Pursuit",
      "icon": "ability_demonhunter_infernalstrike2",
      "spellId": 320654
    },
    "90936": {
      "name": "Soul Rending",
      "icon": "ability_demonhunter_soulcleave2",
      "spellId": 204909
    },
    "117852": {
      "name": "Soul Rending",
      "icon": "ability_demonhunter_soulcleave2",
      "spellId": 204909
    },
    "90939": {
      "name": "Felfire Haste",
      "icon": "inv_boots_cloth_35v4",
      "spellId": 389846
    },
    "117855": {
      "name": "Felfire Haste",
      "icon": "inv_boots_cloth_35v4",
      "spellId": 389846
    },
    "91004": {
      "name": "Infernal Armor",
      "icon": "ability_demonhunter_immolation",
      "spellId": 320331
    },
    "117929": {
      "name": "Infernal Armor",
      "icon": "ability_demonhunter_immolation",
      "spellId": 320331
    },
    "90927": {
      "name": "Burn It Out",
      "icon": "spell_fel_elementaldevastation",
      "spellId": 1266316
    },
    "117842": {
      "name": "Burn It Out",
      "icon": "spell_fel_elementaldevastation",
      "spellId": 1266316
    },
    "141275": {
      "name": "Soul Cleanse",
      "icon": "spell_nature_removecurse",
      "spellId": 1266496
    },
    "90947": {
      "name": "Lost in Darkness",
      "icon": "inv_pet_inquisitoreye",
      "spellId": 389849
    },
    "117865": {
      "name": "Lost in Darkness",
      "icon": "inv_pet_inquisitoreye",
      "spellId": 389849
    },
    "90935": {
      "name": "Illidari Knowledge",
      "icon": "spell_mage_overpowered",
      "spellId": 389696
    },
    "117851": {
      "name": "Illidari Knowledge",
      "icon": "spell_mage_overpowered",
      "spellId": 389696
    },
    "107346": {
      "name": "Guile",
      "icon": "spell_shadow_demonform",
      "spellId": 1223171
    },
    "137089": {
      "name": "Guile",
      "icon": "spell_shadow_demonform",
      "spellId": 1223171
    },
    "91000": {
      "name": "Will of the Illidari",
      "icon": "ability_demonhunter_spectank",
      "spellId": 389695
    },
    "117923": {
      "name": "Will of the Illidari",
      "icon": "ability_demonhunter_spectank",
      "spellId": 389695
    },
    "90934": {
      "name": "Internal Struggle",
      "icon": "ability_warlock_demonicpower",
      "spellId": 393822
    },
    "117850": {
      "name": "Internal Struggle",
      "icon": "ability_warlock_demonicpower",
      "spellId": 393822
    },
    "95152": {
      "name": "Furious",
      "icon": "ability_warlock_shadowfurytga",
      "spellId": 1266326
    },
    "122774": {
      "name": "Furious",
      "icon": "ability_warlock_shadowfurytga",
      "spellId": 1266326
    },
    "90929": {
      "name": "Remorseless",
      "icon": "inv_glaive_1h_npc_d_02",
      "spellId": 1266328
    },
    "117844": {
      "name": "Remorseless",
      "icon": "inv_glaive_1h_npc_d_02",
      "spellId": 1266328
    },
    "95149": {
      "name": "First In, Last Out",
      "icon": "ability_demonhunter_demonictrample",
      "spellId": 1266497
    },
    "122770": {
      "name": "First In, Last Out",
      "icon": "ability_demonhunter_demonictrample",
      "spellId": 1266497
    },
    "90996": {
      "name": "Erratic Felheart",
      "icon": "inv_archaeology_70_crystallineeyeofundravius",
      "spellId": 391397
    },
    "117919": {
      "name": "Erratic Felheart",
      "icon": "inv_archaeology_70_crystallineeyeofundravius",
      "spellId": 391397
    },
    "110011": {
      "name": "Final Breath",
      "icon": "spell_fire_felflamebreath",
      "spellId": 1266500
    },
    "141274": {
      "name": "Final Breath",
      "icon": "spell_fire_felflamebreath",
      "spellId": 1266500
    },
    "91002": {
      "name": "Darkness",
      "icon": "ability_demonhunter_darkness",
      "spellId": 196718
    },
    "117926": {
      "name": "Darkness",
      "icon": "ability_demonhunter_darkness",
      "spellId": 196718
    },
    "90928": {
      "name": "Demon Muzzle",
      "icon": "spell_warlock_demonicservitude",
      "spellId": 1266329
    },
    "117843": {
      "name": "Demon Muzzle",
      "icon": "spell_warlock_demonicservitude",
      "spellId": 1266329
    },
    "90949": {
      "name": "Soul Splitter",
      "icon": "ability_warlock_soulswap",
      "spellId": 1266330
    },
    "117867": {
      "name": "Soul Splitter",
      "icon": "ability_warlock_soulswap",
      "spellId": 1266330
    },
    "110010": {
      "name": "Wings of Wrath",
      "icon": "ability_demonhunter_glide",
      "spellId": 1266493
    },
    "141273": {
      "name": "Wings of Wrath",
      "icon": "ability_demonhunter_glide",
      "spellId": 1266493
    },
    "91001": {
      "name": "Long Night",
      "icon": "spell_fire_twilightimmolation",
      "spellId": 389781
    },
    "117925": {
      "name": "Long Night",
      "icon": "spell_fire_twilightimmolation",
      "spellId": 389781
    },
    "117924": {
      "name": "Pitch Black",
      "icon": "sha_spell_warlock_demonsoul",
      "spellId": 389783
    },
    "90997": {
      "name": "Demonic Resilience",
      "icon": "inv_summondemonictyrant",
      "spellId": 1266307
    },
    "122767": {
      "name": "Demonic Resilience",
      "icon": "inv_summondemonictyrant",
      "spellId": 1266307
    },
    "90912": {
      "name": "",
      "icon": "",
      "spellId": 0
    },
    "107336": {
      "name": "Void Ray",
      "icon": "inv_12_dh_void_ability_voidray",
      "spellId": 473728
    },
    "137079": {
      "name": "Void Ray",
      "icon": "inv_12_dh_void_ability_voidray",
      "spellId": 473728
    },
    "107344": {
      "name": "Soul Immolation",
      "icon": "inv_12_dh_void_ability_voidpurge",
      "spellId": 1241937
    },
    "137087": {
      "name": "Soul Immolation",
      "icon": "inv_12_dh_void_ability_voidpurge",
      "spellId": 1241937
    },
    "107771": {
      "name": "Predator's Thirst",
      "icon": "inv_12_dh_void_ability_consume",
      "spellId": 1215617
    },
    "137893": {
      "name": "Predator's Thirst",
      "icon": "inv_12_dh_void_ability_consume",
      "spellId": 1215617
    },
    "108727": {
      "name": "Tempered Soul",
      "icon": "inv_12_dh_void_ability_voidpurge",
      "spellId": 1246555
    },
    "139053": {
      "name": "Tempered Soul",
      "icon": "inv_12_dh_void_ability_voidpurge",
      "spellId": 1246555
    },
    "140485": {
      "name": "Spontaneous Immolation",
      "icon": "spell_fire_twilightimmolation",
      "spellId": 1246556
    },
    "107340": {
      "name": "Void Metamorphosis",
      "icon": "inv_112_ability_demonhunter_metamorphasisvoid",
      "spellId": 471306
    },
    "137083": {
      "name": "Void Metamorphosis",
      "icon": "inv_112_ability_demonhunter_metamorphasisvoid",
      "spellId": 471306
    },
    "107343": {
      "name": "Feast of Souls",
      "icon": "inv_12_dh_void_ability_firstofsouls",
      "spellId": 1237270
    },
    "137086": {
      "name": "Feast of Souls",
      "icon": "inv_12_dh_void_ability_firstofsouls",
      "spellId": 1237270
    },
    "108726": {
      "name": "Scythe's Embrace",
      "icon": "inv_12_dh_void_ability_voidreaper",
      "spellId": 1246558
    },
    "139052": {
      "name": "Scythe's Embrace",
      "icon": "inv_12_dh_void_ability_voidreaper",
      "spellId": 1246558
    },
    "139048": {
      "name": "Duty Eternal",
      "icon": "inv_12_voiddh_ability_voidblade",
      "spellId": 1246562
    },
    "107339": {
      "name": "Collapsing Star",
      "icon": "inv_12_dh_void_ability_collapsingstar",
      "spellId": 1221167
    },
    "137082": {
      "name": "Collapsing Star",
      "icon": "inv_12_dh_void_ability_collapsingstar",
      "spellId": 1221167
    },
    "107770": {
      "name": "Moment of Craving",
      "icon": "inv_12_dh_void_ability_momentofcraving",
      "spellId": 1238488
    },
    "137892": {
      "name": "Moment of Craving",
      "icon": "inv_12_dh_void_ability_momentofcraving",
      "spellId": 1238488
    },
    "107775": {
      "name": "Gift of the Void",
      "icon": "ability_demonhunter_reversemagic",
      "spellId": 1272847
    },
    "137897": {
      "name": "Gift of the Void",
      "icon": "ability_demonhunter_reversemagic",
      "spellId": 1272847
    },
    "108122": {
      "name": "Entropy",
      "icon": "inv_112_raidtrinkets_voidprism",
      "spellId": 1261684
    },
    "138297": {
      "name": "Entropy",
      "icon": "inv_112_raidtrinkets_voidprism",
      "spellId": 1261684
    },
    "107999": {
      "name": "Waste Not",
      "icon": "inv_12_dh_void_ability_wastenot",
      "spellId": 1223918
    },
    "138156": {
      "name": "Waste Not",
      "icon": "inv_12_dh_void_ability_wastenot",
      "spellId": 1223918
    },
    "107342": {
      "name": "Soulshaper",
      "icon": "inv_12_dh_void_ability_sunder",
      "spellId": 1238739
    },
    "137085": {
      "name": "Soulshaper",
      "icon": "inv_12_dh_void_ability_sunder",
      "spellId": 1238739
    },
    "108627": {
      "name": "Singed Spirit",
      "icon": "inv_11_0_misc_candlekobold_color3",
      "spellId": 1272832
    },
    "138928": {
      "name": "Singed Spirit",
      "icon": "inv_11_0_misc_candlekobold_color3",
      "spellId": 1272832
    },
    "107338": {
      "name": "Sweet Suffering",
      "icon": "ability_demonhunter_shatteredsouls",
      "spellId": 1244295
    },
    "137081": {
      "name": "Sweet Suffering",
      "icon": "ability_demonhunter_shatteredsouls",
      "spellId": 1244295
    },
    "110009": {
      "name": "Second Helping",
      "icon": "inv_polearm_2h_voidscythe_d_01",
      "spellId": 1239537
    },
    "141272": {
      "name": "Second Helping",
      "icon": "inv_polearm_2h_voidscythe_d_01",
      "spellId": 1239537
    },
    "107997": {
      "name": "Umbral Blade",
      "icon": "inv_12_dh_void_ability_reap",
      "spellId": 1272842
    },
    "138154": {
      "name": "Umbral Blade",
      "icon": "inv_12_dh_void_ability_reap",
      "spellId": 1272842
    },
    "108144": {
      "name": "Improved Consume",
      "icon": "inv_12_dh_void_ability_feast",
      "spellId": 1272817
    },
    "139102": {
      "name": "Improved Consume",
      "icon": "inv_12_dh_void_ability_feast",
      "spellId": 1272817
    },
    "108628": {
      "name": "Sweet Release",
      "icon": "spell_misc_zandalari_council_soulswap",
      "spellId": 1242768
    },
    "138929": {
      "name": "Sweet Release",
      "icon": "spell_misc_zandalari_council_soulswap",
      "spellId": 1242768
    },
    "110174": {
      "name": "Voidpurge",
      "icon": "inv_12_dh_void_ability_voidray",
      "spellId": 1244220
    },
    "141471": {
      "name": "Voidpurge",
      "icon": "inv_12_dh_void_ability_voidray",
      "spellId": 1244220
    },
    "108136": {
      "name": "Hungering Slash",
      "icon": "inv_12_dh_void_ability_reapersslice",
      "spellId": 1239519
    },
    "138317": {
      "name": "Hungering Slash",
      "icon": "inv_12_dh_void_ability_reapersslice",
      "spellId": 1239519
    },
    "109871": {
      "name": "Voidrage",
      "icon": "inv_12_dh_void_ability_soulimmolation",
      "spellId": 1242956
    },
    "140886": {
      "name": "Voidrage",
      "icon": "inv_12_dh_void_ability_soulimmolation",
      "spellId": 1242956
    },
    "107774": {
      "name": "Focused Ray",
      "icon": "inv_cosmicvoid_beam",
      "spellId": 1240203
    },
    "137896": {
      "name": "Focused Ray",
      "icon": "inv_cosmicvoid_beam",
      "spellId": 1240203
    },
    "110171": {
      "name": "Soulforged Blades",
      "icon": "inv12_ability_deathknight_frostscythe",
      "spellId": 1272432
    },
    "141468": {
      "name": "Soulforged Blades",
      "icon": "inv12_ability_deathknight_frostscythe",
      "spellId": 1272432
    },
    "110170": {
      "name": "Singular Strikes",
      "icon": "inv_12_dh_void_ability_scythethrow",
      "spellId": 1272770
    },
    "141467": {
      "name": "Singular Strikes",
      "icon": "inv_12_dh_void_ability_scythethrow",
      "spellId": 1272770
    },
    "110165": {
      "name": "Demonic Instinct",
      "icon": "inv_12_dh_void_ability_predatorsthirst",
      "spellId": 1247538
    },
    "141462": {
      "name": "Demonic Instinct",
      "icon": "inv_12_dh_void_ability_predatorsthirst",
      "spellId": 1247538
    },
    "108143": {
      "name": "Devourer's Edge",
      "icon": "inv_12_dh_void_ability_empoweredreap",
      "spellId": 1244222
    },
    "138324": {
      "name": "Devourer's Edge",
      "icon": "inv_12_dh_void_ability_empoweredreap",
      "spellId": 1244222
    },
    "110169": {
      "name": "Voidglare Boon",
      "icon": "inv_nulllotus_cosmicvoid",
      "spellId": 1240202
    },
    "141466": {
      "name": "Voidglare Boon",
      "icon": "inv_nulllotus_cosmicvoid",
      "spellId": 1240202
    },
    "110168": {
      "name": "Rolling Torment",
      "icon": "inv_cosmicvoid_debuff",
      "spellId": 1244237
    },
    "141465": {
      "name": "Rolling Torment",
      "icon": "inv_cosmicvoid_debuff",
      "spellId": 1244237
    },
    "110173": {
      "name": "Voidrush",
      "icon": "inv_12_dh_void_ability_voidstep",
      "spellId": 1272422
    },
    "141470": {
      "name": "Voidrush",
      "icon": "inv_12_dh_void_ability_voidstep",
      "spellId": 1272422
    },
    "110167": {
      "name": "Devourer's Bite",
      "icon": "inv_12_dh_void_ability_devourerbite",
      "spellId": 1240201
    },
    "141464": {
      "name": "Devourer's Bite",
      "icon": "inv_12_dh_void_ability_devourerbite",
      "spellId": 1240201
    },
    "107341": {
      "name": "Impending Apocalypse",
      "icon": "inv_12_dh_void_ability_impendingapocalypse",
      "spellId": 1227707
    },
    "137084": {
      "name": "Impending Apocalypse",
      "icon": "inv_12_dh_void_ability_impendingapocalypse",
      "spellId": 1227707
    },
    "110166": {
      "name": "Calamitous",
      "icon": "ability_argus_soulbombdebuffsmall",
      "spellId": 1242495
    },
    "141463": {
      "name": "Calamitous",
      "icon": "ability_argus_soulbombdebuffsmall",
      "spellId": 1242495
    },
    "110172": {
      "name": "Star Fragments",
      "icon": "inv_12_dh_void_ability_starfragments",
      "spellId": 1240204
    },
    "141469": {
      "name": "Star Fragments",
      "icon": "inv_12_dh_void_ability_starfragments",
      "spellId": 1240204
    },
    "109503": {
      "name": "The Hunt",
      "icon": "inv_12_voiddh_ability_thehunt",
      "spellId": 1246167
    },
    "140491": {
      "name": "The Hunt",
      "icon": "inv_12_voiddh_ability_thehunt",
      "spellId": 1246167
    },
    "108123": {
      "name": "Emptiness",
      "icon": "inv_cosmicvoid_buff",
      "spellId": 1242492
    },
    "138298": {
      "name": "Emptiness",
      "icon": "inv_cosmicvoid_buff",
      "spellId": 1242492
    },
    "139103": {
      "name": "Soul Glutton",
      "icon": "ability_bossgorefiend_gorefiendscorruption",
      "spellId": 1247534
    },
    "107345": {
      "name": "Eradicate",
      "icon": "inv_12_dh_void_ability_eradicate",
      "spellId": 1226033
    },
    "137088": {
      "name": "Eradicate",
      "icon": "inv_12_dh_void_ability_eradicate",
      "spellId": 1226033
    },
    "110416": {
      "name": "Midnight",
      "icon": "inv12_apextalent_demonhunter_midnight",
      "spellId": 1242486
    },
    "141779": {
      "name": "Midnight",
      "icon": "inv12_apextalent_demonhunter_midnight",
      "spellId": 1242486
    },
    "141778": {
      "name": "Midnight",
      "icon": "inv_ability_voidweaverpriest_entropicrift",
      "spellId": 1250088
    },
    "141777": {
      "name": "Midnight",
      "icon": "ability_argus_edgeofobliteration",
      "spellId": 1250094
    },
    "110114": {
      "name": "Wave of Debilitation",
      "icon": "spell_fire_felfirenova",
      "spellId": 452403
    },
    "141394": {
      "name": "Wave of Debilitation",
      "icon": "spell_fire_felfirenova",
      "spellId": 452403
    },
    "141392": {
      "name": "Pursuit of Angriness",
      "icon": "ability_felarakkoa_focusedblast",
      "spellId": 452404
    },
    "110113": {
      "name": "Focused Hatred",
      "icon": "ability_demonhunter_illidansgrasp",
      "spellId": 452405
    },
    "141385": {
      "name": "Focused Hatred",
      "icon": "ability_demonhunter_illidansgrasp",
      "spellId": 452405
    },
    "110117": {
      "name": "Set Fire to the Pain",
      "icon": "ability_demonhunter_empowerwards",
      "spellId": 452406
    },
    "141393": {
      "name": "Set Fire to the Pain",
      "icon": "ability_demonhunter_empowerwards",
      "spellId": 452406
    },
    "141391": {
      "name": "Improved Soul Rending",
      "icon": "ability_demonhunter_soulcleave2",
      "spellId": 452407
    },
    "110105": {
      "name": "Blind Focus",
      "icon": "inv_belt_leather_raiddemonhunter_r_01",
      "spellId": 1272364
    },
    "141380": {
      "name": "Blind Focus",
      "icon": "inv_belt_leather_raiddemonhunter_r_01",
      "spellId": 1272364
    },
    "110111": {
      "name": "Burning Blades",
      "icon": "inv_glaive_1h_artifactazgalor_d_02dual",
      "spellId": 452408
    },
    "141383": {
      "name": "Burning Blades",
      "icon": "inv_glaive_1h_artifactazgalor_d_02dual",
      "spellId": 452408
    },
    "110115": {
      "name": "Violent Transformation",
      "icon": "spell_shadow_demoniccirclesummon",
      "spellId": 452409
    },
    "141395": {
      "name": "Violent Transformation",
      "icon": "spell_shadow_demoniccirclesummon",
      "spellId": 452409
    },
    "110106": {
      "name": "Enduring Torment",
      "icon": "spell_fire_felimmolation",
      "spellId": 452410
    },
    "141388": {
      "name": "Enduring Torment",
      "icon": "spell_fire_felimmolation",
      "spellId": 452410
    },
    "110108": {
      "name": "Undying Embers",
      "icon": "ability_warlock_burningembersgreen",
      "spellId": 1272405
    },
    "141382": {
      "name": "Undying Embers",
      "icon": "ability_warlock_burningembersgreen",
      "spellId": 1272405
    },
    "110109": {
      "name": "Untethered Fury",
      "icon": "inv__felbarrage",
      "spellId": 452411
    },
    "141379": {
      "name": "Untethered Fury",
      "icon": "inv__felbarrage",
      "spellId": 452411
    },
    "110107": {
      "name": "Student of Suffering",
      "icon": "achievement_dungeon_theatreofpain_kultharok",
      "spellId": 452412
    },
    "141389": {
      "name": "Student of Suffering",
      "icon": "achievement_dungeon_theatreofpain_kultharok",
      "spellId": 452412
    },
    "141387": {
      "name": "Flamebound",
      "icon": "spell_fire_felflamering",
      "spellId": 452413
    },
    "110104": {
      "name": "Monster Rising",
      "icon": "ability_warlock_demonicpower",
      "spellId": 452414
    },
    "141381": {
      "name": "Monster Rising",
      "icon": "ability_warlock_demonicpower",
      "spellId": 452414
    },
    "110110": {
      "name": "Volatile Instinct",
      "icon": "inv_nature_nova",
      "spellId": 1272453
    },
    "141384": {
      "name": "Volatile Instinct",
      "icon": "inv_nature_nova",
      "spellId": 1272453
    },
    "110116": {
      "name": "Demonic Intensity",
      "icon": "spell_warlock_demonicempowerment",
      "spellId": 452415
    },
    "141390": {
      "name": "Demonic Intensity",
      "icon": "spell_warlock_demonicempowerment",
      "spellId": 452415
    },
    "109454": {
      "name": "Swift Erasure",
      "icon": "ability_priest_darkarchangel",
      "spellId": 1253668
    },
    "140428": {
      "name": "Swift Erasure",
      "icon": "ability_priest_darkarchangel",
      "spellId": 1253668
    },
    "109455": {
      "name": "Meteoric Rise",
      "icon": "ability_socererking_arcanefortification",
      "spellId": 1253377
    },
    "140429": {
      "name": "Meteoric Rise",
      "icon": "ability_socererking_arcanefortification",
      "spellId": 1253377
    },
    "109453": {
      "name": "Catastrophe",
      "icon": "inv_netherportal",
      "spellId": 1253769
    },
    "140427": {
      "name": "Catastrophe",
      "icon": "inv_netherportal",
      "spellId": 1253769
    },
    "109452": {
      "name": "Phase Shift",
      "icon": "ability_demonhunter_blur",
      "spellId": 1256245
    },
    "140426": {
      "name": "Phase Shift",
      "icon": "ability_demonhunter_blur",
      "spellId": 1256245
    },
    "109448": {
      "name": "Path to Oblivion",
      "icon": "ability_socererking_arcaneacceleration",
      "spellId": 1253399
    },
    "140422": {
      "name": "Path to Oblivion",
      "icon": "ability_socererking_arcaneacceleration",
      "spellId": 1253399
    },
    "140415": {
      "name": "State of Matter",
      "icon": "inv_112_arcane_buff",
      "spellId": 1253402
    },
    "109447": {
      "name": "Mass Acceleration",
      "icon": "inv_nullstone_cosmicvoid",
      "spellId": 1256295
    },
    "140421": {
      "name": "Mass Acceleration",
      "icon": "inv_nullstone_cosmicvoid",
      "spellId": 1256295
    },
    "109450": {
      "name": "Doomsayer",
      "icon": "inv_shadowflame_buff",
      "spellId": 1253676
    },
    "140424": {
      "name": "Doomsayer",
      "icon": "inv_shadowflame_buff",
      "spellId": 1253676
    },
    "141573": {
      "name": "Harness the Cosmos",
      "icon": "inv_cosmicvoid_orb",
      "spellId": 1279247
    },
    "109451": {
      "name": "Celestial Echoes",
      "icon": "inv_polearm_2h_voidscythe_d_01",
      "spellId": 1253415
    },
    "140425": {
      "name": "Celestial Echoes",
      "icon": "inv_polearm_2h_voidscythe_d_01",
      "spellId": 1253415
    },
    "109445": {
      "name": "Final Hour",
      "icon": "inv_10_worlddroplevelingoptionalreagent_relics_hourglass_color1",
      "spellId": 1253805
    },
    "140419": {
      "name": "Final Hour",
      "icon": "inv_10_worlddroplevelingoptionalreagent_relics_hourglass_color1",
      "spellId": 1253805
    },
    "109446": {
      "name": "Meteoric Fall",
      "icon": "ability_socererking_arcanereplication",
      "spellId": 1253391
    },
    "140420": {
      "name": "Meteoric Fall",
      "icon": "ability_socererking_arcanereplication",
      "spellId": 1253391
    },
    "109444": {
      "name": "Dark Matter",
      "icon": "inv_cosmicvoid_nova",
      "spellId": 1256307
    },
    "140418": {
      "name": "Dark Matter",
      "icon": "inv_cosmicvoid_nova",
      "spellId": 1256307
    },
    "109443": {
      "name": "Otherworldly Focus",
      "icon": "inv_babyvoidwalker_blue",
      "spellId": 1253817
    },
    "140417": {
      "name": "Otherworldly Focus",
      "icon": "inv_babyvoidwalker_blue",
      "spellId": 1253817
    },
    "109442": {
      "name": "World Killer",
      "icon": "inv_112_raiddimensius_brokenworld",
      "spellId": 1256353
    },
    "140416": {
      "name": "World Killer",
      "icon": "inv_112_raiddimensius_brokenworld",
      "spellId": 1256353
    }
  },
  "subTrees": {
    "124": {
      "name": "Annihilator",
      "icon": "talents-heroclass-demonhunter-annihilator"
    },
    "126": {
      "name": "Void-Scarred",
      "icon": "talents-heroclass-demonhunter-felscarred2"
    }
  }
}