{
  "specName": "Fury",
  "className": "Warrior",
  "talents": {
    "90344": {
      "name": "Fast Footwork",
      "icon": "ability_hunter_posthaste",
      "spellId": 382260
    },
    "90328": {
      "name": "War Machine",
      "icon": "ability_hunter_rapidkilling",
      "spellId": 262231
    },
    "90343": {
      "name": "Thunder Clap",
      "icon": "spell_nature_thunderclap",
      "spellId": 6343
    },
    "90371": {
      "name": "Leeching Strikes",
      "icon": "inv_artifact_bloodoftheassassinated",
      "spellId": 382258
    },
    "90326": {
      "name": "Impending Victory",
      "icon": "spell_impending_victory",
      "spellId": 202168
    },
    "90346": {
      "name": "Heroic Leap",
      "icon": "ability_heroicleap",
      "spellId": 6544
    },
    "95959": {
      "name": "Crackling Thunder",
      "icon": "ability_thunderking_overcharge",
      "spellId": 203201
    },
    "90337": {
      "name": "Storm Bolt",
      "icon": "warrior_talent_icon_stormbolt",
      "spellId": 107570
    },
    "109391": {
      "name": "Rend",
      "icon": "ability_gouge",
      "spellId": 772
    },
    "90332": {
      "name": "Second Wind",
      "icon": "ability_hunter_harass",
      "spellId": 29838
    },
    "90352": {
      "name": "Frothing Berserker",
      "icon": "warrior_talent_icon_furyintheblood",
      "spellId": 392792
    },
    "90355": {
      "name": "Bounding Stride",
      "icon": "ability_heroicleap",
      "spellId": 202163
    },
    "90353": {
      "name": "Pain and Gain",
      "icon": "spell_holy_painsupression",
      "spellId": 382549
    },
    "108674": {
      "name": "Intervene",
      "icon": "ability_warrior_victoryrush",
      "spellId": 3411
    },
    "90375": {
      "name": "Shockwave",
      "icon": "ability_warrior_shockwave",
      "spellId": 46968
    },
    "90378": {
      "name": "Overwhelming Rage",
      "icon": "racial_orc_berserkerstrength",
      "spellId": 382767
    },
    "90331": {
      "name": "Rallying Cry",
      "icon": "ability_warrior_rallyingcry",
      "spellId": 97462
    },
    "110119": {
      "name": "Field Dressing",
      "icon": "inv_misc_bandage_08",
      "spellId": 1271926
    },
    "90385": {
      "name": "Spell Reflection",
      "icon": "ability_warrior_shieldreflection",
      "spellId": 23920
    },
    "90351": {
      "name": "Wrecking Throw",
      "icon": "warrior_talent_icon_mastercleaver",
      "spellId": 384110
    },
    "90374": {
      "name": "Rumbling Earth",
      "icon": "spell_shaman_earthquake",
      "spellId": 275339
    },
    "90348": {
      "name": "Berserker Shout",
      "icon": "spell_nature_ancestralguardian",
      "spellId": 384100
    },
    "108705": {
      "name": "Intimidating Shout",
      "icon": "ability_golemthunderclap",
      "spellId": 5246
    },
    "95956": {
      "name": "Honed Reflexes",
      "icon": "spell_holy_borrowedtime",
      "spellId": 391271
    },
    "90366": {
      "name": "Armored to the Teeth",
      "icon": "inv_shoulder_22",
      "spellId": 384124
    },
    "90382": {
      "name": "Double Time",
      "icon": "inv_misc_horn_04",
      "spellId": 103827
    },
    "90368": {
      "name": "Reinforced Plates",
      "icon": "inv_chest_plate04",
      "spellId": 382939
    },
    "90347": {
      "name": "Barbaric Training",
      "icon": "ability_garrosh_whirling_corruption",
      "spellId": 383082
    },
    "110118": {
      "name": "Javelineer",
      "icon": "inv_spear_01",
      "spellId": 1271948
    },
    "108685": {
      "name": "Resonant Voice",
      "icon": "warrior_disruptingshout",
      "spellId": 1243660
    },
    "108686": {
      "name": "Crushing Force",
      "icon": "spell_shadow_unholystrength",
      "spellId": 382764
    },
    "90381": {
      "name": "Cruel Strikes",
      "icon": "ability_criticalstrike",
      "spellId": 392777
    },
    "90373": {
      "name": "Dual Wield Specialization",
      "icon": "ability_dualwield",
      "spellId": 382900
    },
    "90360": {
      "name": "Wild Strikes",
      "icon": "ability_rogue_sprint",
      "spellId": 382946
    },
    "108543": {
      "name": "Anger Management",
      "icon": "warrior_talent_icon_angermanagement",
      "spellId": 152278
    },
    "90380": {
      "name": "Champion's Spear",
      "icon": "inv_ability_warrior_championsspear",
      "spellId": 376079
    },
    "108542": {
      "name": "Stance Mastery",
      "icon": "crest_warrior",
      "spellId": 1280961
    },
    "108544": {
      "name": "Battlefield Commander",
      "icon": "ability_warrior_commandingshout",
      "spellId": 424742
    },
    "90392": {
      "name": "Bloodthirst",
      "icon": "spell_nature_bloodlust",
      "spellId": 23881
    },
    "90396": {
      "name": "Raging Blow",
      "icon": "warrior_wild_strike",
      "spellId": 85288
    },
    "90430": {
      "name": "Sudden Death",
      "icon": "ability_warrior_improveddisciplines",
      "spellId": 29725
    },
    "90398": {
      "name": "Frenzied Enrage",
      "icon": "spell_shadow_unholyfrenzy",
      "spellId": 383848
    },
    "90429": {
      "name": "Improved Execute",
      "icon": "inv_sword_48",
      "spellId": 316402
    },
    "90403": {
      "name": "Focus in Chaos",
      "icon": "ability_hunter_mastermarksman",
      "spellId": 383486
    },
    "90395": {
      "name": "Enraged Regeneration",
      "icon": "ability_warrior_focusedrage",
      "spellId": 184364
    },
    "90394": {
      "name": "Warpaint",
      "icon": "ability_rogue_preparation",
      "spellId": 208154
    },
    "90427": {
      "name": "Improved Whirlwind",
      "icon": "ability_whirlwind",
      "spellId": 12950
    },
    "90410": {
      "name": "Massacre",
      "icon": "inv_axe_2h_orcwarrior_c_01",
      "spellId": 206315
    },
    "90399": {
      "name": "Fresh Meat",
      "icon": "ability_deathwing_bloodcorruption_death",
      "spellId": 215568
    },
    "110330": {
      "name": "Invigorating Fury",
      "icon": "spell_misc_emotionangry",
      "spellId": 383468
    },
    "90408": {
      "name": "Rampage",
      "icon": "ability_warrior_rampage",
      "spellId": 184367
    },
    "90390": {
      "name": "Improved Raging Blow",
      "icon": "warrior_wild_strike",
      "spellId": 383854
    },
    "90391": {
      "name": "Rampaging Ruin",
      "icon": "ability_warrior_trauma",
      "spellId": 1265357
    },
    "109966": {
      "name": "Deep Wounds",
      "icon": "ability_backstab",
      "spellId": 1261060
    },
    "90397": {
      "name": "Spite",
      "icon": "warrior_talent_icon_furyintheblood",
      "spellId": 383852
    },
    "109969": {
      "name": "Scent of Blood",
      "icon": "ability_hunter_harass",
      "spellId": 1265355
    },
    "109965": {
      "name": "Kill or Be Killed",
      "icon": "inv12_ability_warrior_fury",
      "spellId": 1265361
    },
    "90407": {
      "name": "Hack and Slash",
      "icon": "ability_rogue_rollthebones02",
      "spellId": 383877
    },
    "90428": {
      "name": "Cruelty",
      "icon": "spell_nature_focusedmind",
      "spellId": 392931
    },
    "109967": {
      "name": "Meat Cleaver",
      "icon": "warrior_talent_icon_mastercleaver",
      "spellId": 280392
    },
    "90402": {
      "name": "Cold Steel, Hot Blood",
      "icon": "ability_rogue_hungerforblood",
      "spellId": 383959
    },
    "109962": {
      "name": "Ragedrinker",
      "icon": "spell_nzinsanity_bloodthirst",
      "spellId": 1265356
    },
    "90412": {
      "name": "Recklessness",
      "icon": "warrior_talent_icon_innerrage",
      "spellId": 1719
    },
    "90405": {
      "name": "Bloodcraze",
      "icon": "ability_creature_cursed_02",
      "spellId": 393950
    },
    "90387": {
      "name": "Wrath and Fury",
      "icon": "inv_sword_2h_artifactarathor_d_03",
      "spellId": 392936
    },
    "90421": {
      "name": "Deft Experience",
      "icon": "inv_misc_book_07",
      "spellId": 383295
    },
    "90406": {
      "name": "Frenzy",
      "icon": "ability_rogue_bloodyeye",
      "spellId": 335077
    },
    "90425": {
      "name": "Critical Thinking",
      "icon": "ability_criticalstrike",
      "spellId": 383297
    },
    "109963": {
      "name": "Vicious Contempt",
      "icon": "ability_ironmaidens_sorkasprey",
      "spellId": 383885
    },
    "110203": {
      "name": "Odyn's Fury",
      "icon": "inv_sword_1h_artifactvigfus_d_01",
      "spellId": 385059
    },
    "90401": {
      "name": "Bloodborne",
      "icon": "inv_artifact_bloodoftheassassinated",
      "spellId": 385703
    },
    "109964": {
      "name": "Surge of Adrenaline",
      "icon": "inv_1115_warrior_fasterreflexes",
      "spellId": 1265359
    },
    "109968": {
      "name": "Executioner's Wrath",
      "icon": "inv_12_nonmasculinecharacter_human",
      "spellId": 1265570
    },
    "90388": {
      "name": "Reckless Abandon",
      "icon": "spell_fire_incinerate",
      "spellId": 396749
    },
    "90415": {
      "name": "Avatar",
      "icon": "warrior_talent_icon_avatar",
      "spellId": 107574
    },
    "110412": {
      "name": "Rampaging Berserker",
      "icon": "inv12_apextalent_warrior_rampagingberserker2",
      "spellId": 1269308
    },
    "94816": {
      "name": "Crashing Thunder",
      "icon": "spell_nature_thunderclap",
      "spellId": 436707
    },
    "94800": {
      "name": "Ground Current",
      "icon": "warrior_talent_icon_thunderstruck",
      "spellId": 436148
    },
    "94808": {
      "name": "Strength of the Mountain",
      "icon": "ability_warrior_titansgrip",
      "spellId": 437068
    },
    "109811": {
      "name": "Storm Surge",
      "icon": "ability_racial_avatar",
      "spellId": 275336
    },
    "94785": {
      "name": "Thunder Blast",
      "icon": "warrior_talent_icon_bloodandthunder",
      "spellId": 435607
    },
    "94817": {
      "name": "Storm Bolts",
      "icon": "warrior_talent_icon_stormbolt",
      "spellId": 436162
    },
    "94798": {
      "name": "Keep Your Feet on the Ground",
      "icon": "ability_thunderking_overcharge",
      "spellId": 438590
    },
    "109810": {
      "name": "Conductivity",
      "icon": "spell_shaman_thunderstorm",
      "spellId": 1270723
    },
    "94788": {
      "name": "Imminent Demise",
      "icon": "ability_warrior_improveddisciplines",
      "spellId": 444769
    },
    "94810": {
      "name": "Overwhelming Blades",
      "icon": "inv_10_specialization_blacksmithing_blades_color1",
      "spellId": 444772
    },
    "94795": {
      "name": "Relentless Pursuit",
      "icon": "ability_rogue_sprint",
      "spellId": 444776
    },
    "109817": {
      "name": "Violent Euphoria",
      "icon": "ability_butcher_exsanguination",
      "spellId": 1270717
    },
    "94797": {
      "name": "Flashing Skies",
      "icon": "spell_lightning_lightningbolt01",
      "spellId": 437079
    },
    "94792": {
      "name": "Gathering Clouds",
      "icon": "spell_nature_stormreach",
      "spellId": 436201
    },
    "94807": {
      "name": "Burst of Power",
      "icon": "shaman_pvp_thundercharge",
      "spellId": 437118
    },
    "109809": {
      "name": "Capacitance",
      "icon": "spell_nature_purge",
      "spellId": 1270724
    },
    "94813": {
      "name": "Death Drive",
      "icon": "ability_warrior_focusedrage",
      "spellId": 444770
    },
    "94786": {
      "name": "Culling Cyclone",
      "icon": "ability_warrior_bladestorm",
      "spellId": 444778
    },
    "94787": {
      "name": "Fierce Followthrough",
      "icon": "spell_deathknight_butcher2",
      "spellId": 444773
    },
    "109816": {
      "name": "Deadly Focus",
      "icon": "spell_hunter_focusingshot",
      "spellId": 1270718
    },
    "94805": {
      "name": "Avatar of the Storm",
      "icon": "achievement_dungeon_blackrockcaverns_ascendantlordobsidius",
      "spellId": 437134
    },
    "94784": {
      "name": "Show No Mercy",
      "icon": "warrior_talent_icon_lambstotheslaughter",
      "spellId": 444771
    },
    "94809": {
      "name": "Reap the Storm",
      "icon": "ability_arakkoa_spinning_blade",
      "spellId": 444775
    },
    "94801": {
      "name": "Slayer's Malice",
      "icon": "ability_warrior_revenge",
      "spellId": 444779
    },
    "109815": {
      "name": "Unhinged",
      "icon": "spell_shadow_spectralsight",
      "spellId": 386628
    },
    "94820": {
      "name": "Unrelenting Onslaught",
      "icon": "ability_warrior_commandingshout",
      "spellId": 444780
    }
  },
  "subTrees": {
    "61": {
      "name": "Mountain Thane",
      "icon": "talents-heroclass-warrior-mountainthane"
    },
    "60": {
      "name": "Slayer",
      "icon": "talents-heroclass-warrior-slayer"
    }
  }
}